README.md
setup.py
chronoboa/__init__.py
chronoboa/__main__.py
chronoboa/workshops.py
chronoboa.egg-info/PKG-INFO
chronoboa.egg-info/SOURCES.txt
chronoboa.egg-info/dependency_links.txt
chronoboa.egg-info/entry_points.txt
chronoboa.egg-info/requires.txt
chronoboa.egg-info/top_level.txt