Metadata-Version: 2.1
Name: chronoboa
Version: 0.1.1
Summary: Paquete permite consumir el API de CodigoFacilito
Home-page: https://gitlab.com/V-Juarez/cruds/-/tree/pypi
Author: Victoriano
Author-email: mytacam78@gmail.com
License: MIT
Keywords: codigofacilto
Platform: UNKNOWN
Classifier: Development Status :: 3 - Alpha
Classifier: Intended Audience :: Developers
Classifier: Topic :: Software Development :: Build Tools
Classifier: License :: OSI Approved :: MIT License
Classifier: Programming Language :: Python :: 3
